{
  "fdid": "12190",
  "name": "HUMBOLDT CSA4",
  "state": "CA",
  "city": "",
  "zip": "",
  "county": "",
  "num_stations": "",
  "num_ff_career": "",
  "num_ff_volunteer": "",
  "year": 2024,
  "total_incidents": 42,
  "incident_types": {
    "hazmat": 19,
    "other": 10,
    "wildland_fire": 7,
    "vehicle_fire": 3,
    "structure_fire": 3
  },
  "monthly_volume": {
    "2020-01": 3,
    "2020-02": 2,
    "2020-03": 2,
    "2020-04": 2,
    "2020-05": 5,
    "2020-06": 4,
    "2020-07": 6,
    "2020-08": 3,
    "2020-09": 2,
    "2020-10": 1,
    "2020-11": 10,
    "2020-12": 2
  }
}